pyekv/__init__.py
pyekv-0.1.3.dist-info/METADATA
pyekv-0.1.3.dist-info/WHEEL
pyekv-0.1.3.dist-info/top_level.txt
pyekv-0.1.3.dist-info/RECORD
