Metadata-Version: 2.4
Name: pyekv
Version: 0.1.3
Summary: Simple, SQLite-backed KV storage. Best suited for prototypes, tools, or local scripts.
Requires-Python: >=3.11
